{
  "Version": "4.0.0", 
  "Began": "Tue Jul 29 17:11:28 2025", 
  "Command line": "/people/tang584/install/ior/bin/ior -a POSIX -t 100m -b 100m -F -C -e -k -o /tmp/tang584/aws_1n_test/16_ts100m_bs100m_t2 -O summaryFormat=JSON -O summaryFile=/qfs/projects/datamesh/tang584/ERT4IO/aws_fuse_bench/1n_result_ior_16_ts100m_bs100m_t2/16_ts100m_bs100m_t2.json", 
  "Machine": "Linux dc001.local", 
  "tests": [
    {
    "TestID": 0, 
    "StartTime": "Tue Jul 29 17:11:28 2025"    , "Path": "/tmp/tang584/aws_1n_test/16_ts100m_bs100m_t2.00000000","Capacity": "-8589934592.0 GiB", "Used Capacity": "0.0%","Inodes": "8796093022208.0 Mi", "Used Inodes" : "0.0%"
, 
    "Parameters": {
      "testID": 0, 
      "refnum": 0, 
      "api": "POSIX", 
      "platform": "dc001.local(Linux)", 
      "testFileName": "/tmp/tang584/aws_1n_test/16_ts100m_bs100m_t2", 
      "deadlineForStonewall": 0, 
      "stoneWallingWearOut": 0, 
      "maxTimeDuration": 0, 
      "outlierThreshold": 0, 
      "options": "(null)", 
      "dryRun": 0, 
      "nodes": 1, 
      "memoryPerTask": 0, 
      "memoryPerNode": 0, 
      "tasksPerNode": 16, 
      "repetitions": 1, 
      "multiFile": 0, 
      "interTestDelay": 0, 
      "fsync": 1, 
      "fsyncperwrite": 0, 
      "useExistingTestFile": 0, 
      "uniqueDir": 0, 
      "singleXferAttempt": 0, 
      "readFile": 1, 
      "writeFile": 1, 
      "filePerProc": 1, 
      "reorderTasks": 1, 
      "reorderTasksRandom": 0, 
      "reorderTasksRandomSeed": 0, 
      "randomOffset": 0, 
      "checkWrite": 0, 
      "checkRead": 0, 
      "dataPacketType": 0, 
      "keepFile": 1, 
      "keepFileWithError": 0, 
      "warningAsErrors": 0, 
      "verbose": 0, 
      "data packet type": "g", 
      "setTimeStampSignature/incompressibleSeed": 0, 
      "collective": 0, 
      "segmentCount": 1, 
      "transferSize": 104857600, 
      "blockSize": 104857600
    }
, 
    "Options": {
      "api": "POSIX", 
      "apiVersion": "", 
      "test filename": "/tmp/tang584/aws_1n_test/16_ts100m_bs100m_t2", 
      "access": "file-per-process", 
      "type": "independent", 
      "segments": 1, 
      "ordering in a file": "sequential", 
      "ordering inter file": "constant task offset", 
      "task offset": 1, 
      "nodes": 1, 
      "tasks": 16, 
      "clients per node": 16, 
      "repetitions": 1, 
      "xfersize": "100 MiB", 
      "blocksize": "100 MiB", 
      "aggregate filesize": "1.56 GiB"
    }
, 
    "Results": [
            {
        "access": "write", 
        "bwMiB": 111.6569, 
        "blockKiB": 102400.0000, 
        "xferKiB": 102400.0000, 
        "iops": 1.1168, 
        "latency": 13.9474, 
        "openTime": 0.0193, 
        "wrRdTime": 14.3273, 
        "closeTime": 3.5538, 
        "totalTime": 14.3296
      }
, 
            {
        "access": "read", 
        "bwMiB": 31766.3066, 
        "blockKiB": 102400.0000, 
        "xferKiB": 102400.0000, 
        "iops": 324.4121, 
        "latency": 0.0457, 
        "openTime": 0.0010, 
        "wrRdTime": 0.0493, 
        "closeTime": 0.0269, 
        "totalTime": 0.0504
      }
]

  }
]
, 
"summary": [
    {
    "operation": "write", 
    "API": "POSIX", 
    "TestID": 0, 
    "ReferenceNumber": 0, 
    "segmentCount": 1, 
    "blockSize": 104857600, 
    "transferSize": 104857600, 
    "numTasks": 16, 
    "tasksPerNode": 16, 
    "repetitions": 1, 
    "filePerProc": 1, 
    "reorderTasks": 1, 
    "taskPerNodeOffset": 1, 
    "reorderTasksRandom": 0, 
    "reorderTasksRandomSeed": 0, 
    "bwMaxMIB": 111.6569, 
    "bwMinMIB": 111.6569, 
    "bwMeanMIB": 111.6569, 
    "bwStdMIB": 0.0000, 
    "OPsMax": 1.1166, 
    "OPsMin": 1.1166, 
    "OPsMean": 1.1166, 
    "OPsSD": 0.0000, 
    "MeanTime": 14.3296, 
    "xsizeMiB": 1600.0000
  }
, 
    {
    "operation": "read", 
    "API": "POSIX", 
    "TestID": 0, 
    "ReferenceNumber": 0, 
    "segmentCount": 1, 
    "blockSize": 104857600, 
    "transferSize": 104857600, 
    "numTasks": 16, 
    "tasksPerNode": 16, 
    "repetitions": 1, 
    "filePerProc": 1, 
    "reorderTasks": 1, 
    "taskPerNodeOffset": 1, 
    "reorderTasksRandom": 0, 
    "reorderTasksRandomSeed": 0, 
    "bwMaxMIB": 31766.3066, 
    "bwMinMIB": 31766.3066, 
    "bwMeanMIB": 31766.3066, 
    "bwStdMIB": 0.0000, 
    "OPsMax": 317.6631, 
    "OPsMin": 317.6631, 
    "OPsMean": 317.6631, 
    "OPsSD": 0.0000, 
    "MeanTime": 0.0504, 
    "xsizeMiB": 1600.0000
  }
]
, 
"Finished": "Tue Jul 29 17:11:42 2025"
}
